{
    "Alignment" : null,
    "Point" : null,
    "actors" : [
        {
            "Alignment" : [ 0, 0 ],
            "Alpha" : 1.0,
            "Angle" : 0.0,
            "Colour" : 4294967295,
            "Flip" : 0,
            "Position" : [ 0.0, 0.0 ],
            "Scale" : [ 1.25, 1.25 ],
            "Shown" : true,
            "sprite" : "tackshooter_fierytack",
            "type" : 1,
            "uid" : 1
         }
    ],
    "customvariables" : null,
    "events" : null,
    "labels" : null,
    "stageOptions" : {
       "SpriteInfo" : [
          {
             "SpriteInfo" : "tackshooter_fierytack",
             "Texture" : "tackshooter"
          }
       ],
       "StageLength" : 0.0,
       "Version" : 1
    },
    "timelines" : [
        {
            "spriteuid" : 1,
            "stage" : null
         }
    ]
 }
 